pelican/plugins/simple_footnotes/__init__.py
pelican/plugins/simple_footnotes/simple_footnotes.py
pelican/plugins/simple_footnotes/test_simple_footnotes.py
pelican_simple_footnotes-1.0.3.dist-info/METADATA
pelican_simple_footnotes-1.0.3.dist-info/WHEEL
pelican_simple_footnotes-1.0.3.dist-info/licenses/LICENSE
pelican_simple_footnotes-1.0.3.dist-info/RECORD
